<?xml version="1.0"?>
<!DOCTYPE hibernate-mapping PUBLIC "-//Hibernate/Hibernate Mapping DTD 3.0//EN" "http://hibernate.sourceforge.net/hibernate-mapping-3.0.dtd">

<hibernate-mapping default-lazy="false" auto-import="false">
	<import class="com.ext.portlet.model.ActivitySubscription" />
	<import class="com.ext.portlet.model.AnalyticsUserEvent" />
	<import class="com.ext.portlet.model.BalloonLink" />
	<import class="com.ext.portlet.model.BalloonStatsEntry" />
	<import class="com.ext.portlet.model.BalloonText" />
	<import class="com.ext.portlet.model.BalloonUserTracking" />
	<import class="com.ext.portlet.model.Contest" />
	<import class="com.ext.portlet.model.ContestDebate" />
	<import class="com.ext.portlet.model.ContestDiscussion" />
	<import class="com.ext.portlet.model.ContestEmailTemplate" />
	<import class="com.ext.portlet.model.ContestPhase" />
	<import class="com.ext.portlet.model.ContestPhaseColumn" />
	<import class="com.ext.portlet.model.ContestPhaseRibbonType" />
	<import class="com.ext.portlet.model.ContestPhaseType" />
	<import class="com.ext.portlet.model.ContestSchedule" />
	<import class="com.ext.portlet.model.ContestTeamMember" />
	<import class="com.ext.portlet.model.DiscussionCategory" />
	<import class="com.ext.portlet.model.DiscussionCategoryGroup" />
	<import class="com.ext.portlet.model.DiscussionMessage" />
	<import class="com.ext.portlet.model.DiscussionMessageFlag" />
	<import class="com.ext.portlet.model.EmailList" />
	<import class="com.ext.portlet.model.FocusArea" />
	<import class="com.ext.portlet.model.FocusAreaOntologyTerm" />
	<import class="com.ext.portlet.model.ImpactDefaultSeries" />
	<import class="com.ext.portlet.model.ImpactDefaultSeriesData" />
	<import class="com.ext.portlet.model.ImpactIteration" />
	<import class="com.ext.portlet.model.ImpactTemplateFocusAreaList" />
	<import class="com.ext.portlet.model.ImpactTemplateMaxFocusArea" />
	<import class="com.ext.portlet.model.ImpactTemplateSeries" />
	<import class="com.ext.portlet.model.LandingPage" />
	<import class="com.ext.portlet.model.LoginLog" />
	<import class="com.ext.portlet.model.Message" />
	<import class="com.ext.portlet.model.MessageRecipientStatus" />
	<import class="com.ext.portlet.model.MessagingIgnoredRecipients" />
	<import class="com.ext.portlet.model.MessagingMessage" />
	<import class="com.ext.portlet.model.MessagingMessageConversion" />
	<import class="com.ext.portlet.model.MessagingMessageConversionType" />
	<import class="com.ext.portlet.model.MessagingMessageRecipient" />
	<import class="com.ext.portlet.model.MessagingRedirectLink" />
	<import class="com.ext.portlet.model.MessagingUserPreferences" />
	<import class="com.ext.portlet.model.ModelCategory" />
	<import class="com.ext.portlet.model.ModelDiscussion" />
	<import class="com.ext.portlet.model.ModelGlobalPreference" />
	<import class="com.ext.portlet.model.ModelInputGroup" />
	<import class="com.ext.portlet.model.ModelInputItem" />
	<import class="com.ext.portlet.model.ModelOutputChartOrder" />
	<import class="com.ext.portlet.model.ModelOutputItem" />
	<import class="com.ext.portlet.model.ModelPosition" />
	<import class="com.ext.portlet.model.ModelRunner" />
	<import class="com.ext.portlet.model.OntologySpace" />
	<import class="com.ext.portlet.model.OntologyTerm" />
	<import class="com.ext.portlet.model.OntologyTermEntity" />
	<import class="com.ext.portlet.model.Plan2Proposal" />
	<import class="com.ext.portlet.model.PlanAttribute" />
	<import class="com.ext.portlet.model.PlanAttributeFilter" />
	<import class="com.ext.portlet.model.PlanColumnSettings" />
	<import class="com.ext.portlet.model.PlanDescription" />
	<import class="com.ext.portlet.model.PlanFan" />
	<import class="com.ext.portlet.model.PlanItem" />
	<import class="com.ext.portlet.model.PlanItemGroup" />
	<import class="com.ext.portlet.model.PlanMeta" />
	<import class="com.ext.portlet.model.PlanModelRun" />
	<import class="com.ext.portlet.model.PlanPosition" />
	<import class="com.ext.portlet.model.PlanPositionItem" />
	<import class="com.ext.portlet.model.PlanPositions" />
	<import class="com.ext.portlet.model.PlanPropertyFilter" />
	<import class="com.ext.portlet.model.PlanRelated" />
	<import class="com.ext.portlet.model.PlanSection" />
	<import class="com.ext.portlet.model.PlanSectionDefinition" />
	<import class="com.ext.portlet.model.PlanSectionPlanMap" />
	<import class="com.ext.portlet.model.PlansFilter" />
	<import class="com.ext.portlet.model.PlansFilterPosition" />
	<import class="com.ext.portlet.model.PlansUserSettings" />
	<import class="com.ext.portlet.model.PlanTeamHistory" />
	<import class="com.ext.portlet.model.PlanTemplate" />
	<import class="com.ext.portlet.model.PlanTemplateSection" />
	<import class="com.ext.portlet.model.PlanType" />
	<import class="com.ext.portlet.model.PlanTypeAttribute" />
	<import class="com.ext.portlet.model.PlanTypeColumn" />
	<import class="com.ext.portlet.model.PlanVote" />
	<import class="com.ext.portlet.model.PointDistributionTarget" />
	<import class="com.ext.portlet.model.Points" />
	<import class="com.ext.portlet.model.PointsDistributionConfiguration" />
	<import class="com.ext.portlet.model.PointType" />
	<import class="com.ext.portlet.model.Proposal" />
	<import class="com.ext.portlet.model.Proposal2Phase" />
	<import class="com.ext.portlet.model.ProposalAttribute" />
	<import class="com.ext.portlet.model.ProposalAttributeType" />
	<import class="com.ext.portlet.model.ProposalContestPhaseAttribute" />
	<import class="com.ext.portlet.model.ProposalContestPhaseAttributeType" />
	<import class="com.ext.portlet.model.ProposalRating" />
	<import class="com.ext.portlet.model.ProposalRatingType" />
	<import class="com.ext.portlet.model.ProposalRatingValue" />
	<import class="com.ext.portlet.model.ProposalSupporter" />
	<import class="com.ext.portlet.model.ProposalVersion" />
	<import class="com.ext.portlet.model.ProposalVote" />
	<import class="com.ext.portlet.model.Role_" />
	<import class="com.ext.portlet.model.RolesCategory" />
	<import class="com.ext.portlet.model.SocialActivity" />
	<import class="com.ext.portlet.model.StaffMember" />
	<import class="com.ext.portlet.model.TrackedVisit" />
	<import class="com.ext.portlet.model.TrackedVisitor2User" />
	<import class="com.ext.portlet.model.User_" />
	<import class="com.ext.portlet.model.Users_Roles" />
	<class name="com.ext.portlet.model.impl.ActivitySubscriptionImpl" table="xcolab_ActivitySubscription">
		<cache usage="read-write" />
		<id name="pk" type="long">
			<generator class="assigned" />
		</id>
		<property name="classNameId" type="com.liferay.portal.dao.orm.hibernate.LongType" />
		<property name="classPK" type="com.liferay.portal.dao.orm.hibernate.LongType" />
		<property name="type" type="com.liferay.portal.dao.orm.hibernate.IntegerType" column="type_" />
		<property name="automaticSubscriptionCounter" type="com.liferay.portal.dao.orm.hibernate.IntegerType" />
		<property name="extraData" type="com.liferay.portal.dao.orm.hibernate.StringType" />
		<property name="receiverId" type="com.liferay.portal.dao.orm.hibernate.LongType" />
		<property name="createDate" type="org.hibernate.type.TimestampType" />
		<property name="modifiedDate" type="org.hibernate.type.TimestampType" />
	</class>
	<class name="com.ext.portlet.model.impl.AnalyticsUserEventImpl" table="xcolab_AnalyticsUserEvent">
		<cache usage="read-write" />
		<composite-id name="primaryKey" class="com.ext.portlet.service.persistence.AnalyticsUserEventPK">
			<key-property name="userId" type="com.liferay.portal.dao.orm.hibernate.LongType" />
			<key-property name="idString" type="com.liferay.portal.dao.orm.hibernate.StringType" />
		</composite-id>
		<property name="category" type="com.liferay.portal.dao.orm.hibernate.StringType" />
		<property name="action" type="com.liferay.portal.dao.orm.hibernate.StringType" />
		<property name="label" type="com.liferay.portal.dao.orm.hibernate.StringType" />
		<property name="value" type="com.liferay.portal.dao.orm.hibernate.IntegerType" />
		<property name="created" type="org.hibernate.type.TimestampType" />
	</class>
	<class name="com.ext.portlet.model.impl.BalloonLinkImpl" table="xcolab_BalloonLink">
		<cache usage="read-write" />
		<id name="uuid" column="uuid_" type="java.lang.String">
			<generator class="assigned" />
		</id>
		<property name="targetUrl" type="com.liferay.portal.dao.orm.hibernate.StringType" />
		<property name="visits" type="com.liferay.portal.dao.orm.hibernate.IntegerType" />
		<property name="balloonUserUuid" type="com.liferay.portal.dao.orm.hibernate.StringType" />
		<property name="createDate" type="org.hibernate.type.TimestampType" />
	</class>
	<class name="com.ext.portlet.model.impl.BalloonStatsEntryImpl" table="xcolab_BalloonStatsEntry">
		<cache usage="read-write" />
		<id name="id" column="id_" type="long">
			<generator class="assigned" />
		</id>
		<property name="firstContestId" type="com.liferay.portal.dao.orm.hibernate.LongType" />
		<property name="secondContestId" type="com.liferay.portal.dao.orm.hibernate.LongType" />
		<property name="choosenContest" type="com.liferay.portal.dao.orm.hibernate.IntegerType" />
		<property name="cookie" type="com.liferay.portal.dao.orm.hibernate.StringType" />
		<property name="ip" type="com.liferay.portal.dao.orm.hibernate.StringType" />
		<property name="extraData" type="com.liferay.portal.dao.orm.hibernate.StringType" />
	</class>
	<class name="com.ext.portlet.model.impl.BalloonTextImpl" table="xcolab_BalloonText">
		<cache usage="read-write" />
		<id name="id" column="id_" type="long">
			<generator class="assigned" />
		</id>
		<property name="name" type="com.liferay.portal.dao.orm.hibernate.StringType" />
		<property name="textBeforeForm" type="com.liferay.portal.dao.orm.hibernate.StringType" />
		<property name="textAfterForm" type="com.liferay.portal.dao.orm.hibernate.StringType" />
		<property name="textBeforeShareButtons" type="com.liferay.portal.dao.orm.hibernate.StringType" />
		<property name="textAfterShareButtons" type="com.liferay.portal.dao.orm.hibernate.StringType" />
		<property name="acceptTosText" type="com.liferay.portal.dao.orm.hibernate.StringType" />
		<property name="emailTemplate" type="com.liferay.portal.dao.orm.hibernate.StringType" />
		<property name="emailSubjectTemplate" type="com.liferay.portal.dao.orm.hibernate.StringType" />
		<property name="twitterDescription" type="com.liferay.portal.dao.orm.hibernate.StringType" />
		<property name="twitterSubject" type="com.liferay.portal.dao.orm.hibernate.StringType" />
		<property name="facebookDescription" type="com.liferay.portal.dao.orm.hibernate.StringType" />
		<property name="facebookSubject" type="com.liferay.portal.dao.orm.hibernate.StringType" />
		<property name="enabled" type="com.liferay.portal.dao.orm.hibernate.BooleanType" />
	</class>
	<class name="com.ext.portlet.model.impl.BalloonUserTrackingImpl" table="xcolab_BalloonUserTracking">
		<cache usage="read-write" />
		<id name="uuid" column="uuid_" type="java.lang.String">
			<generator class="assigned" />
		</id>
		<property name="email" type="com.liferay.portal.dao.orm.hibernate.StringType" />
		<property name="parent" type="com.liferay.portal.dao.orm.hibernate.StringType" />
		<property name="ip" type="com.liferay.portal.dao.orm.hibernate.StringType" />
		<property name="createDate" type="org.hibernate.type.TimestampType" />
		<property name="registrationDate" type="org.hibernate.type.TimestampType" />
		<property name="formFiledDate" type="org.hibernate.type.TimestampType" />
		<property name="userId" type="com.liferay.portal.dao.orm.hibernate.LongType" />
		<property name="balloonTextId" type="com.liferay.portal.dao.orm.hibernate.LongType" />
		<property name="referrer" type="com.liferay.portal.dao.orm.hibernate.StringType" />
		<property name="latitude" type="com.liferay.portal.dao.orm.hibernate.DoubleType" />
		<property name="longitude" type="com.liferay.portal.dao.orm.hibernate.DoubleType" />
		<property name="city" type="com.liferay.portal.dao.orm.hibernate.StringType" />
		<property name="country" type="com.liferay.portal.dao.orm.hibernate.StringType" />
		<property name="extraData" type="com.liferay.portal.dao.orm.hibernate.StringType" />
		<property name="balloonLinkUuid" type="com.liferay.portal.dao.orm.hibernate.StringType" />
		<property name="balloonLinkContext" type="com.liferay.portal.dao.orm.hibernate.StringType" />
		<property name="userAgent" type="com.liferay.portal.dao.orm.hibernate.StringType" />
	</class>
	<class name="com.ext.portlet.model.impl.ContestImpl" table="xcolab_Contest">
		<cache usage="read-write" />
		<id name="ContestPK" type="long">
			<generator class="assigned" />
		</id>
		<property name="ContestName" type="com.liferay.portal.dao.orm.hibernate.StringType" />
		<property name="ContestShortName" type="com.liferay.portal.dao.orm.hibernate.StringType" />
		<property name="ContestDescription" type="com.liferay.portal.dao.orm.hibernate.StringType" />
		<property name="ContestModelDescription" type="com.liferay.portal.dao.orm.hibernate.StringType" />
		<property name="ContestPositionsDescription" type="com.liferay.portal.dao.orm.hibernate.StringType" />
		<property name="defaultPlanDescription" type="com.liferay.portal.dao.orm.hibernate.StringType" />
		<property name="PlanTypeId" type="com.liferay.portal.dao.orm.hibernate.LongType" />
		<property name="created" type="org.hibernate.type.TimestampType" />
		<property name="updated" type="org.hibernate.type.TimestampType" />
		<property name="authorId" type="com.liferay.portal.dao.orm.hibernate.LongType" />
		<property name="contestActive" type="com.liferay.portal.dao.orm.hibernate.BooleanType" />
		<property name="planTemplateId" type="com.liferay.portal.dao.orm.hibernate.LongType" />
		<property name="contestScheduleId" type="com.liferay.portal.dao.orm.hibernate.LongType" />
		<property name="focusAreaId" type="com.liferay.portal.dao.orm.hibernate.LongType" />
		<property name="contestTier" type="com.liferay.portal.dao.orm.hibernate.LongType" />
		<property name="contestLogoId" type="com.liferay.portal.dao.orm.hibernate.LongType" />
		<property name="featured" type="com.liferay.portal.dao.orm.hibernate.BooleanType" column="featured_" />
		<property name="plansOpenByDefault" type="com.liferay.portal.dao.orm.hibernate.BooleanType" />
		<property name="sponsorLogoId" type="com.liferay.portal.dao.orm.hibernate.LongType" />
		<property name="sponsorText" type="com.liferay.portal.dao.orm.hibernate.StringType" />
		<property name="sponsorLink" type="com.liferay.portal.dao.orm.hibernate.StringType" />
		<property name="flag" type="com.liferay.portal.dao.orm.hibernate.IntegerType" />
		<property name="flagText" type="com.liferay.portal.dao.orm.hibernate.StringType" />
		<property name="flagTooltip" type="com.liferay.portal.dao.orm.hibernate.StringType" />
		<property name="groupId" type="com.liferay.portal.dao.orm.hibernate.LongType" />
		<property name="discussionGroupId" type="com.liferay.portal.dao.orm.hibernate.LongType" />
		<property name="weight" type="com.liferay.portal.dao.orm.hibernate.IntegerType" />
		<property name="resourcesUrl" type="com.liferay.portal.dao.orm.hibernate.StringType" />
		<property name="contestPrivate" type="com.liferay.portal.dao.orm.hibernate.BooleanType" />
		<property name="usePermissions" type="com.liferay.portal.dao.orm.hibernate.BooleanType" />
		<property name="contestCreationStatus" type="com.liferay.portal.dao.orm.hibernate.StringType" />
		<property name="defaultModelId" type="com.liferay.portal.dao.orm.hibernate.LongType" />
		<property name="otherModels" type="com.liferay.portal.dao.orm.hibernate.StringType" />
		<property name="points" type="com.liferay.portal.dao.orm.hibernate.DoubleType" />
		<property name="defaultParentPointType" type="com.liferay.portal.dao.orm.hibernate.LongType" />
		<property name="pointDistributionStrategy" type="com.liferay.portal.dao.orm.hibernate.StringType" />
		<property name="emailTemplateUrl" type="com.liferay.portal.dao.orm.hibernate.StringType" />
		<property name="show_in_tile_view" type="com.liferay.portal.dao.orm.hibernate.BooleanType" />
		<property name="show_in_list_view" type="com.liferay.portal.dao.orm.hibernate.BooleanType" />
		<property name="show_in_outline_view" type="com.liferay.portal.dao.orm.hibernate.BooleanType" />
	</class>
	<class name="com.ext.portlet.model.impl.ContestDebateImpl" table="xcolab_ContestDebate">
		<cache usage="read-write" />
		<id name="id" column="id_" type="long">
			<generator class="assigned" />
		</id>
		<property name="debateId" type="com.liferay.portal.dao.orm.hibernate.LongType" />
		<property name="ContestPK" type="com.liferay.portal.dao.orm.hibernate.LongType" />
	</class>
	<class name="com.ext.portlet.model.impl.ContestDiscussionImpl" table="xcolab_ContestDiscussion">
		<cache usage="read-write" />
		<id name="DiscussionId" type="long">
			<generator class="assigned" />
		</id>
		<property name="ContestId" type="com.liferay.portal.dao.orm.hibernate.LongType" />
		<property name="Tab" type="com.liferay.portal.dao.orm.hibernate.StringType" />
	</class>
	<class name="com.ext.portlet.model.impl.ContestEmailTemplateImpl" table="xcolab_ContestEmailTemplate">
		<cache usage="read-write" />
		<id name="type" column="type_" type="java.lang.String">
			<generator class="assigned" />
		</id>
		<property name="subject" type="com.liferay.portal.dao.orm.hibernate.StringType" />
		<property name="header" type="com.liferay.portal.dao.orm.hibernate.StringType" />
		<property name="footer" type="com.liferay.portal.dao.orm.hibernate.StringType" />
	</class>
	<class name="com.ext.portlet.model.impl.ContestPhaseImpl" table="xcolab_ContestPhase">
		<cache usage="read-write" />
		<id name="ContestPhasePK" type="long">
			<generator class="assigned" />
		</id>
		<property name="ContestPK" type="com.liferay.portal.dao.orm.hibernate.LongType" />
		<property name="ContestPhaseType" type="com.liferay.portal.dao.orm.hibernate.LongType" />
		<property name="contestScheduleId" type="com.liferay.portal.dao.orm.hibernate.LongType" />
		<property name="fellowScreeningActive" type="com.liferay.portal.dao.orm.hibernate.BooleanType" />
		<property name="contestPhaseAutopromote" type="com.liferay.portal.dao.orm.hibernate.StringType" />
		<property name="ContestPhaseDescriptionOverride" type="com.liferay.portal.dao.orm.hibernate.StringType" />
		<property name="phaseActiveOverride" type="com.liferay.portal.dao.orm.hibernate.BooleanType" />
		<property name="phaseInactiveOverride" type="com.liferay.portal.dao.orm.hibernate.BooleanType" />
		<property name="PhaseStartDate" type="org.hibernate.type.TimestampType" />
		<property name="PhaseEndDate" type="org.hibernate.type.TimestampType" />
		<property name="PhaseBufferEndDated" type="org.hibernate.type.TimestampType" />
		<property name="nextStatus" type="com.liferay.portal.dao.orm.hibernate.StringType" />
		<property name="created" type="org.hibernate.type.TimestampType" />
		<property name="updated" type="org.hibernate.type.TimestampType" />
		<property name="authorId" type="com.liferay.portal.dao.orm.hibernate.LongType" />
	</class>
	<class name="com.ext.portlet.model.impl.ContestPhaseColumnImpl" table="xcolab_ContestPhaseColumn">
		<cache usage="read-write" />
		<id name="id" column="id_" type="long">
			<generator class="assigned" />
		</id>
		<property name="ContestPhasePK" type="com.liferay.portal.dao.orm.hibernate.LongType" />
		<property name="columnName" type="com.liferay.portal.dao.orm.hibernate.StringType" />
		<property name="columnWeight" type="com.liferay.portal.dao.orm.hibernate.IntegerType" />
		<property name="defaultSort" type="com.liferay.portal.dao.orm.hibernate.BooleanType" />
	</class>
	<class name="com.ext.portlet.model.impl.ContestPhaseRibbonTypeImpl" table="xcolab_ContestPhaseRibbonType">
		<cache usage="read-write" />
		<id name="id" column="id_" type="long">
			<generator class="assigned" />
		</id>
		<property name="ribbon" type="com.liferay.portal.dao.orm.hibernate.IntegerType" />
		<property name="hoverText" type="com.liferay.portal.dao.orm.hibernate.StringType" />
		<property name="description" type="com.liferay.portal.dao.orm.hibernate.StringType" />
		<property name="copyOnPromote" type="com.liferay.portal.dao.orm.hibernate.BooleanType" />
	</class>
	<class name="com.ext.portlet.model.impl.ContestPhaseTypeImpl" table="xcolab_ContestPhaseType">
		<cache usage="read-write" />
		<id name="id" column="id_" type="long">
			<generator class="assigned" />
		</id>
		<property name="name" type="com.liferay.portal.dao.orm.hibernate.StringType" />
		<property name="description" type="com.liferay.portal.dao.orm.hibernate.StringType" />
		<property name="status" type="com.liferay.portal.dao.orm.hibernate.StringType" />
		<property name="fellowScreeningActiveDefault" type="com.liferay.portal.dao.orm.hibernate.BooleanType" />
		<property name="contestPhaseAutopromoteDefault" type="com.liferay.portal.dao.orm.hibernate.StringType" />
		<property name="invisible" type="com.liferay.portal.dao.orm.hibernate.BooleanType" />
		<property name="pointsAccessible" type="com.liferay.portal.dao.orm.hibernate.IntegerType" />
	</class>
	<class name="com.ext.portlet.model.impl.ContestScheduleImpl" table="xcolab_ContestSchedule">
		<cache usage="read-write" />
		<id name="id" column="id_" type="long">
			<generator class="assigned" />
		</id>
		<property name="name" type="com.liferay.portal.dao.orm.hibernate.StringType" />
		<property name="description" type="com.liferay.portal.dao.orm.hibernate.StringType" />
		<property name="status" type="com.liferay.portal.dao.orm.hibernate.StringType" />
		<property name="baseScheduleId" type="com.liferay.portal.dao.orm.hibernate.LongType" />
	</class>
	<class name="com.ext.portlet.model.impl.ContestTeamMemberImpl" table="xcolab_ContestTeamMember">
		<cache usage="read-write" />
		<id name="id" column="id_" type="long">
			<generator class="assigned" />
		</id>
		<property name="contestId" type="com.liferay.portal.dao.orm.hibernate.LongType" />
		<property name="userId" type="com.liferay.portal.dao.orm.hibernate.LongType" />
		<property name="role" type="com.liferay.portal.dao.orm.hibernate.StringType" />
	</class>
	<class name="com.ext.portlet.model.impl.DiscussionCategoryImpl" table="xcolab_DiscussionCategory">
		<cache usage="read-write" />
		<id name="pk" type="long">
			<generator class="assigned" />
		</id>
		<property name="categoryId" type="com.liferay.portal.dao.orm.hibernate.LongType" />
		<property name="categoryGroupId" type="com.liferay.portal.dao.orm.hibernate.LongType" />
		<property name="authorId" type="com.liferay.portal.dao.orm.hibernate.LongType" />
		<property name="name" type="com.liferay.portal.dao.orm.hibernate.StringType" />
		<property name="description" type="com.liferay.portal.dao.orm.hibernate.StringType" />
		<property name="createDate" type="org.hibernate.type.TimestampType" />
		<property name="deleted" type="org.hibernate.type.TimestampType" />
		<property name="threadsCount" type="com.liferay.portal.dao.orm.hibernate.IntegerType" />
		<property name="lastActivityDate" type="org.hibernate.type.TimestampType" />
		<property name="lastActivityAuthorId" type="com.liferay.portal.dao.orm.hibernate.LongType" />
	</class>
	<class name="com.ext.portlet.model.impl.DiscussionCategoryGroupImpl" table="xcolab_DiscussionCategoryGroup">
		<cache usage="read-write" />
		<id name="id" column="id_" type="long">
			<generator class="assigned" />
		</id>
		<property name="description" type="com.liferay.portal.dao.orm.hibernate.StringType" />
		<property name="url" type="com.liferay.portal.dao.orm.hibernate.StringType" />
		<property name="commentsThread" type="com.liferay.portal.dao.orm.hibernate.LongType" />
		<property name="isQuiet" type="com.liferay.portal.dao.orm.hibernate.BooleanType" />
	</class>
	<class name="com.ext.portlet.model.impl.DiscussionMessageImpl" table="xcolab_DiscussionMessage">
		<cache usage="read-write" />
		<id name="pk" type="long">
			<generator class="assigned" />
		</id>
		<property name="messageId" type="com.liferay.portal.dao.orm.hibernate.LongType" />
		<property name="subject" type="com.liferay.portal.dao.orm.hibernate.StringType" />
		<property name="body" type="com.liferay.portal.dao.orm.hibernate.StringType" />
		<property name="threadId" type="com.liferay.portal.dao.orm.hibernate.LongType" />
		<property name="categoryId" type="com.liferay.portal.dao.orm.hibernate.LongType" />
		<property name="categoryGroupId" type="com.liferay.portal.dao.orm.hibernate.LongType" />
		<property name="authorId" type="com.liferay.portal.dao.orm.hibernate.LongType" />
		<property name="createDate" type="org.hibernate.type.TimestampType" />
		<property name="version" type="com.liferay.portal.dao.orm.hibernate.LongType" />
		<property name="deleted" type="org.hibernate.type.TimestampType" />
		<property name="responsesCount" type="com.liferay.portal.dao.orm.hibernate.IntegerType" />
		<property name="lastActivityDate" type="org.hibernate.type.TimestampType" />
		<property name="lastActivityAuthorId" type="com.liferay.portal.dao.orm.hibernate.LongType" />
	</class>
	<class name="com.ext.portlet.model.impl.DiscussionMessageFlagImpl" table="xcolab_DiscussionMessageFlag">
		<cache usage="read-write" />
		<id name="pk" type="long">
			<generator class="assigned" />
		</id>
		<property name="messageId" type="com.liferay.portal.dao.orm.hibernate.LongType" />
		<property name="flagType" type="com.liferay.portal.dao.orm.hibernate.StringType" />
		<property name="data" type="com.liferay.portal.dao.orm.hibernate.StringType" column="data_" />
		<property name="created" type="org.hibernate.type.TimestampType" />
		<property name="userId" type="com.liferay.portal.dao.orm.hibernate.LongType" />
	</class>
	<class name="com.ext.portlet.model.impl.EmailListImpl" table="xcolab_EmailList">
		<cache usage="read-write" />
		<id name="id" column="id_" type="long">
			<generator class="assigned" />
		</id>
		<property name="name" type="com.liferay.portal.dao.orm.hibernate.StringType" />
		<property name="email" type="com.liferay.portal.dao.orm.hibernate.StringType" />
	</class>
	<class name="com.ext.portlet.model.impl.FocusAreaImpl" table="xcolab_FocusArea">
		<cache usage="read-write" />
		<id name="id" column="id_" type="long">
			<generator class="assigned" />
		</id>
		<property name="name" type="com.liferay.portal.dao.orm.hibernate.StringType" />
		<property name="order" type="com.liferay.portal.dao.orm.hibernate.IntegerType" column="order_" />
	</class>
	<class name="com.ext.portlet.model.impl.FocusAreaOntologyTermImpl" table="xcolab_FocusAreaOntologyTerm">
		<cache usage="read-write" />
		<composite-id name="primaryKey" class="com.ext.portlet.service.persistence.FocusAreaOntologyTermPK">
			<key-property name="focusAreaId" type="com.liferay.portal.dao.orm.hibernate.LongType" />
			<key-property name="ontologyTermId" type="com.liferay.portal.dao.orm.hibernate.LongType" />
		</composite-id>
		<property name="order" type="com.liferay.portal.dao.orm.hibernate.IntegerType" column="order_" />
	</class>
	<class name="com.ext.portlet.model.impl.ImpactDefaultSeriesImpl" table="xcolab_ImpactDefaultSeries">
		<cache usage="read-write" />
		<composite-id name="primaryKey" class="com.ext.portlet.service.persistence.ImpactDefaultSeriesPK">
			<key-property name="seriesId" type="com.liferay.portal.dao.orm.hibernate.LongType" />
			<key-property name="name" type="com.liferay.portal.dao.orm.hibernate.StringType" />
		</composite-id>
		<property name="description" type="com.liferay.portal.dao.orm.hibernate.StringType" />
		<property name="focusAreaId" type="com.liferay.portal.dao.orm.hibernate.LongType" />
		<property name="visible" type="com.liferay.portal.dao.orm.hibernate.BooleanType" />
		<property name="editable" type="com.liferay.portal.dao.orm.hibernate.BooleanType" />
	</class>
	<class name="com.ext.portlet.model.impl.ImpactDefaultSeriesDataImpl" table="xcolab_ImpactDefaultSeriesData">
		<cache usage="read-write" />
		<composite-id name="primaryKey" class="com.ext.portlet.service.persistence.ImpactDefaultSeriesDataPK">
			<key-property name="seriesId" type="com.liferay.portal.dao.orm.hibernate.LongType" />
			<key-property name="year" type="com.liferay.portal.dao.orm.hibernate.IntegerType" />
		</composite-id>
		<property name="value" type="com.liferay.portal.dao.orm.hibernate.DoubleType" />
	</class>
	<class name="com.ext.portlet.model.impl.ImpactIterationImpl" table="xcolab_ImpactIteration">
		<cache usage="read-write" />
		<composite-id name="primaryKey" class="com.ext.portlet.service.persistence.ImpactIterationPK">
			<key-property name="iterationId" type="com.liferay.portal.dao.orm.hibernate.LongType" />
			<key-property name="year" type="com.liferay.portal.dao.orm.hibernate.IntegerType" />
		</composite-id>
	</class>
	<class name="com.ext.portlet.model.impl.ImpactTemplateFocusAreaListImpl" table="xcolab_ImpactTemplateFocusAreaList">
		<cache usage="read-write" />
		<id name="focusAreaListId" type="long">
			<generator class="assigned" />
		</id>
		<property name="name" type="com.liferay.portal.dao.orm.hibernate.StringType" />
	</class>
	<class name="com.ext.portlet.model.impl.ImpactTemplateMaxFocusAreaImpl" table="xcolab_ImpactTemplateMaxFocusArea">
		<cache usage="read-write" />
		<composite-id name="primaryKey" class="com.ext.portlet.service.persistence.ImpactTemplateMaxFocusAreaPK">
			<key-property name="focusAreaListId" type="com.liferay.portal.dao.orm.hibernate.LongType" />
			<key-property name="focusAreaId" type="com.liferay.portal.dao.orm.hibernate.LongType" />
		</composite-id>
	</class>
	<class name="com.ext.portlet.model.impl.ImpactTemplateSeriesImpl" table="xcolab_ImpactTemplateSeries">
		<cache usage="read-write" />
		<id name="seriesId" type="long">
			<generator class="assigned" />
		</id>
		<property name="iterationId" type="com.liferay.portal.dao.orm.hibernate.LongType" />
		<property name="name" type="com.liferay.portal.dao.orm.hibernate.StringType" />
	</class>
	<class name="com.ext.portlet.model.impl.LandingPageImpl" table="xcolab_LandingPage">
		<cache usage="read-write" />
		<id name="id" column="id_" type="long">
			<generator class="assigned" />
		</id>
		<property name="baseUrl" type="com.liferay.portal.dao.orm.hibernate.StringType" />
		<property name="targetUrl" type="com.liferay.portal.dao.orm.hibernate.StringType" />
		<property name="updated" type="org.hibernate.type.TimestampType" />
	</class>
	<class name="com.ext.portlet.model.impl.LoginLogImpl" table="xcolab_LoginLog">
		<cache usage="read-write" />
		<id name="pk" type="long">
			<generator class="assigned" />
		</id>
		<property name="userId" type="com.liferay.portal.dao.orm.hibernate.LongType" />
		<property name="createDate" type="org.hibernate.type.TimestampType" />
		<property name="ipAddress" type="com.liferay.portal.dao.orm.hibernate.StringType" />
		<property name="city" type="com.liferay.portal.dao.orm.hibernate.StringType" />
		<property name="country" type="com.liferay.portal.dao.orm.hibernate.StringType" />
		<property name="entryUrl" type="com.liferay.portal.dao.orm.hibernate.StringType" />
	</class>
	<class name="com.ext.portlet.model.impl.MessageImpl" table="xcolab_Message">
		<cache usage="read-write" />
		<id name="messageId" type="long">
			<generator class="assigned" />
		</id>
		<property name="fromId" type="com.liferay.portal.dao.orm.hibernate.LongType" />
		<property name="repliesTo" type="com.liferay.portal.dao.orm.hibernate.LongType" />
		<property name="createDate" type="org.hibernate.type.TimestampType" />
		<property name="subject" type="com.liferay.portal.dao.orm.hibernate.StringType" />
		<property name="content" type="com.liferay.portal.dao.orm.hibernate.StringType" />
	</class>
	<class name="com.ext.portlet.model.impl.MessageRecipientStatusImpl" table="xcolab_MessageRecipientStatus">
		<cache usage="read-write" />
		<id name="messageRecipientId" type="long">
			<generator class="assigned" />
		</id>
		<property name="messageId" type="com.liferay.portal.dao.orm.hibernate.LongType" />
		<property name="userId" type="com.liferay.portal.dao.orm.hibernate.LongType" />
		<property name="opened" type="com.liferay.portal.dao.orm.hibernate.BooleanType" />
		<property name="archived" type="com.liferay.portal.dao.orm.hibernate.BooleanType" />
	</class>
	<class name="com.ext.portlet.model.impl.MessagingIgnoredRecipientsImpl" table="xcolab_MessagingIgnoredRecipients">
		<cache usage="read-write" />
		<id name="ignoredRecipientId" type="long">
			<generator class="assigned" />
		</id>
		<property name="email" type="com.liferay.portal.dao.orm.hibernate.StringType" />
		<property name="name" type="com.liferay.portal.dao.orm.hibernate.StringType" />
		<property name="userId" type="com.liferay.portal.dao.orm.hibernate.LongType" />
		<property name="createDate" type="org.hibernate.type.TimestampType" />
	</class>
	<class name="com.ext.portlet.model.impl.MessagingMessageImpl" table="xcolab_MessagingMessage">
		<cache usage="read-write" />
		<id name="messageId" type="long">
			<generator class="assigned" />
		</id>
		<property name="name" type="com.liferay.portal.dao.orm.hibernate.StringType" />
		<property name="description" type="com.liferay.portal.dao.orm.hibernate.StringType" />
		<property name="subject" type="com.liferay.portal.dao.orm.hibernate.StringType" />
		<property name="body" type="com.liferay.portal.dao.orm.hibernate.StringType" />
		<property name="replyTo" type="com.liferay.portal.dao.orm.hibernate.StringType" />
		<property name="sendToAll" type="com.liferay.portal.dao.orm.hibernate.BooleanType" />
		<property name="conversionCount" type="com.liferay.portal.dao.orm.hibernate.LongType" />
		<property name="redirectURL" type="com.liferay.portal.dao.orm.hibernate.StringType" />
		<property name="creatorId" type="com.liferay.portal.dao.orm.hibernate.LongType" />
		<property name="createDate" type="org.hibernate.type.TimestampType" />
		<property name="modifiedDate" type="org.hibernate.type.TimestampType" />
	</class>
	<class name="com.ext.portlet.model.impl.MessagingMessageConversionImpl" table="xcolab_MessagingMessageConversion">
		<cache usage="read-write" />
		<id name="conversionId" type="long">
			<generator class="assigned" />
		</id>
		<property name="conversionTypeId" type="com.liferay.portal.dao.orm.hibernate.LongType" />
		<property name="messageId" type="com.liferay.portal.dao.orm.hibernate.LongType" />
		<property name="ipAddress" type="com.liferay.portal.dao.orm.hibernate.StringType" />
		<property name="extraData" type="com.liferay.portal.dao.orm.hibernate.StringType" />
		<property name="extraData2" type="com.liferay.portal.dao.orm.hibernate.StringType" />
		<property name="createDate" type="org.hibernate.type.TimestampType" />
	</class>
	<class name="com.ext.portlet.model.impl.MessagingMessageConversionTypeImpl" table="xcolab_MessagingMessageConversionType">
		<cache usage="read-write" />
		<id name="typeId" type="long">
			<generator class="assigned" />
		</id>
		<property name="name" type="com.liferay.portal.dao.orm.hibernate.StringType" />
		<property name="description" type="com.liferay.portal.dao.orm.hibernate.StringType" />
	</class>
	<class name="com.ext.portlet.model.impl.MessagingMessageRecipientImpl" table="xcolab_MessagingMessageRecipient">
		<cache usage="read-write" />
		<id name="recipientId" type="long">
			<generator class="assigned" />
		</id>
		<property name="messageId" type="com.liferay.portal.dao.orm.hibernate.LongType" />
		<property name="userId" type="com.liferay.portal.dao.orm.hibernate.LongType" />
		<property name="emailAddress" type="com.liferay.portal.dao.orm.hibernate.StringType" />
	</class>
	<class name="com.ext.portlet.model.impl.MessagingRedirectLinkImpl" table="xcolab_MessagingRedirectLink">
		<cache usage="read-write" />
		<id name="redirectId" type="long">
			<generator class="assigned" />
		</id>
		<property name="link" type="com.liferay.portal.dao.orm.hibernate.StringType" />
		<property name="messageId" type="com.liferay.portal.dao.orm.hibernate.LongType" />
		<property name="createDate" type="org.hibernate.type.TimestampType" />
	</class>
	<class name="com.ext.portlet.model.impl.MessagingUserPreferencesImpl" table="xcolab_MessagingUserPreferences">
		<cache usage="read-write" />
		<id name="messagingPreferencesId" type="long">
			<generator class="assigned" />
		</id>
		<property name="userId" type="com.liferay.portal.dao.orm.hibernate.LongType" />
		<property name="emailOnSend" type="com.liferay.portal.dao.orm.hibernate.BooleanType" />
		<property name="emailOnReceipt" type="com.liferay.portal.dao.orm.hibernate.BooleanType" />
		<property name="emailOnActivity" type="com.liferay.portal.dao.orm.hibernate.BooleanType" />
		<property name="emailActivityDailyDigest" type="com.liferay.portal.dao.orm.hibernate.BooleanType" />
	</class>
	<class name="com.ext.portlet.model.impl.ModelCategoryImpl" table="xcolab_ModelCategory">
		<cache usage="read-write" />
		<id name="modelCategoryPK" type="long">
			<generator class="assigned" />
		</id>
		<property name="modelCategoryName" type="com.liferay.portal.dao.orm.hibernate.StringType" />
		<property name="modelCategoryDescription" type="com.liferay.portal.dao.orm.hibernate.StringType" />
		<property name="modelCategoryDisplayWeight" type="com.liferay.portal.dao.orm.hibernate.IntegerType" />
	</class>
	<class name="com.ext.portlet.model.impl.ModelDiscussionImpl" table="xcolab_ModelDiscussion">
		<cache usage="read-write" />
		<id name="modelDiscussionId" type="long">
			<generator class="assigned" />
		</id>
		<property name="modelId" type="com.liferay.portal.dao.orm.hibernate.LongType" />
		<property name="categoryId" type="com.liferay.portal.dao.orm.hibernate.LongType" />
	</class>
	<class name="com.ext.portlet.model.impl.ModelGlobalPreferenceImpl" table="xcolab_ModelGlobalPreference">
		<cache usage="read-write" />
		<id name="modelGlobalPreferencePK" type="long">
			<generator class="assigned" />
		</id>
		<property name="modelId" type="com.liferay.portal.dao.orm.hibernate.LongType" />
		<property name="visible" type="com.liferay.portal.dao.orm.hibernate.BooleanType" />
		<property name="weight" type="com.liferay.portal.dao.orm.hibernate.IntegerType" />
		<property name="expertEvaluationPageId" type="com.liferay.portal.dao.orm.hibernate.LongType" />
		<property name="modelCategoryId" type="com.liferay.portal.dao.orm.hibernate.LongType" />
		<property name="usesCustomInputs" type="com.liferay.portal.dao.orm.hibernate.BooleanType" />
		<property name="customInputsDefinition" type="com.liferay.portal.dao.orm.hibernate.StringType" />
	</class>
	<class name="com.ext.portlet.model.impl.ModelInputGroupImpl" table="xcolab_ModelInputGroup">
		<cache usage="read-write" />
		<id name="modelInputGroupPK" type="long">
			<generator class="assigned" />
		</id>
		<property name="modelId" type="com.liferay.portal.dao.orm.hibernate.LongType" />
		<property name="nameAndDescriptionMetaDataId" type="com.liferay.portal.dao.orm.hibernate.LongType" />
		<property name="name" type="com.liferay.portal.dao.orm.hibernate.StringType" />
		<property name="description" type="com.liferay.portal.dao.orm.hibernate.StringType" />
		<property name="displayItemOrder" type="com.liferay.portal.dao.orm.hibernate.IntegerType" />
		<property name="groupType" type="com.liferay.portal.dao.orm.hibernate.StringType" />
		<property name="parentGroupPK" type="com.liferay.portal.dao.orm.hibernate.LongType" />
	</class>
	<class name="com.ext.portlet.model.impl.ModelInputItemImpl" table="xcolab_ModelInputItem">
		<cache usage="read-write" />
		<id name="modelInputItemPK" type="long">
			<generator class="assigned" />
		</id>
		<property name="modelId" type="com.liferay.portal.dao.orm.hibernate.LongType" />
		<property name="modelInputItemID" type="com.liferay.portal.dao.orm.hibernate.LongType" />
		<property name="modelGroupId" type="com.liferay.portal.dao.orm.hibernate.LongType" />
		<property name="displayItemOrder" type="com.liferay.portal.dao.orm.hibernate.IntegerType" />
		<property name="type" type="com.liferay.portal.dao.orm.hibernate.StringType" column="type_" />
		<property name="properties" type="com.liferay.portal.dao.orm.hibernate.StringType" />
	</class>
	<class name="com.ext.portlet.model.impl.ModelOutputChartOrderImpl" table="xcolab_ModelOutputChartOrder">
		<cache usage="read-write" />
		<id name="modelOutputChartOrderPK" type="long">
			<generator class="assigned" />
		</id>
		<property name="modelId" type="com.liferay.portal.dao.orm.hibernate.LongType" />
		<property name="modelOutputLabel" type="com.liferay.portal.dao.orm.hibernate.StringType" />
		<property name="modelOutputChartOrder" type="com.liferay.portal.dao.orm.hibernate.IntegerType" />
		<property name="modelIndexRangePolicy" type="com.liferay.portal.dao.orm.hibernate.StringType" />
		<property name="modelIndexRangeMessage" type="com.liferay.portal.dao.orm.hibernate.StringType" />
		<property name="modelIndexErrorPolicy" type="com.liferay.portal.dao.orm.hibernate.StringType" />
		<property name="modelIndexErrorMessage" type="com.liferay.portal.dao.orm.hibernate.StringType" />
		<property name="modelChartIsVisible" type="com.liferay.portal.dao.orm.hibernate.BooleanType" />
	</class>
	<class name="com.ext.portlet.model.impl.ModelOutputItemImpl" table="xcolab_ModelOutputItem">
		<cache usage="read-write" />
		<id name="modelOutputItemModifierPK" type="long">
			<generator class="assigned" />
		</id>
		<property name="modelId" type="com.liferay.portal.dao.orm.hibernate.LongType" />
		<property name="modelOutputItemId" type="com.liferay.portal.dao.orm.hibernate.LongType" />
		<property name="modelOutputItemOrder" type="com.liferay.portal.dao.orm.hibernate.IntegerType" />
		<property name="modelItemRangePolicy" type="com.liferay.portal.dao.orm.hibernate.StringType" />
		<property name="modelItemRangeMessage" type="com.liferay.portal.dao.orm.hibernate.StringType" />
		<property name="modelItemErrorPolicy" type="com.liferay.portal.dao.orm.hibernate.StringType" />
		<property name="modelItemErrorMessage" type="com.liferay.portal.dao.orm.hibernate.StringType" />
		<property name="modelItemLabelFormat" type="com.liferay.portal.dao.orm.hibernate.StringType" />
		<property name="modelItemIsVisible" type="com.liferay.portal.dao.orm.hibernate.BooleanType" />
		<property name="itemType" type="com.liferay.portal.dao.orm.hibernate.StringType" />
		<property name="relatedOutputItem" type="com.liferay.portal.dao.orm.hibernate.LongType" />
	</class>
	<class name="com.ext.portlet.model.impl.ModelPositionImpl" table="xcolab_ModelPosition">
		<cache usage="read-write" />
		<id name="id" column="id_" type="long">
			<generator class="assigned" />
		</id>
		<property name="positionId" type="com.liferay.portal.dao.orm.hibernate.LongType" />
		<property name="modelId" type="com.liferay.portal.dao.orm.hibernate.LongType" />
	</class>
	<class name="com.ext.portlet.model.impl.OntologySpaceImpl" table="xcolab_OntologySpace">
		<cache usage="read-write" />
		<id name="id" column="id_" type="long">
			<generator class="assigned" />
		</id>
		<property name="name" type="com.liferay.portal.dao.orm.hibernate.StringType" />
		<property name="description" type="com.liferay.portal.dao.orm.hibernate.StringType" />
		<property name="order" type="com.liferay.portal.dao.orm.hibernate.IntegerType" column="order_" />
	</class>
	<class name="com.ext.portlet.model.impl.OntologyTermImpl" table="xcolab_OntologyTerm">
		<cache usage="read-write" />
		<id name="id" column="id_" type="long">
			<generator class="assigned" />
		</id>
		<property name="parentId" type="com.liferay.portal.dao.orm.hibernate.LongType" />
		<property name="ontologySpaceId" type="com.liferay.portal.dao.orm.hibernate.LongType" />
		<property name="name" type="com.liferay.portal.dao.orm.hibernate.StringType" />
		<property name="descriptionUrl" type="com.liferay.portal.dao.orm.hibernate.StringType" />
		<property name="order_" type="com.liferay.portal.dao.orm.hibernate.IntegerType" />
	</class>
	<class name="com.ext.portlet.model.impl.OntologyTermEntityImpl" table="xcolab_OntologyTermEntity">
		<cache usage="read-write" />
		<id name="id" column="id_" type="long">
			<generator class="assigned" />
		</id>
		<property name="termId" type="com.liferay.portal.dao.orm.hibernate.LongType" />
		<property name="classNameId" type="com.liferay.portal.dao.orm.hibernate.LongType" />
		<property name="classPK" type="com.liferay.portal.dao.orm.hibernate.LongType" />
	</class>
	<class name="com.ext.portlet.model.impl.Plan2ProposalImpl" table="xcolab_Plan2Proposal">
		<cache usage="read-write" />
		<id name="planId" type="long">
			<generator class="assigned" />
		</id>
		<property name="proposalId" type="com.liferay.portal.dao.orm.hibernate.LongType" />
	</class>
	<class name="com.ext.portlet.model.impl.PlanAttributeImpl" table="xcolab_PlanAttribute">
		<cache usage="read-write" />
		<id name="attributeId" type="long">
			<generator class="assigned" />
		</id>
		<property name="planId" type="com.liferay.portal.dao.orm.hibernate.LongType" />
		<property name="attributeName" type="com.liferay.portal.dao.orm.hibernate.StringType" />
		<property name="attributeValue" type="com.liferay.portal.dao.orm.hibernate.StringType" />
	</class>
	<class name="com.ext.portlet.model.impl.PlanAttributeFilterImpl" table="xcolab_PlanAttributeFilter">
		<cache usage="read-write" />
		<id name="planAttributeFilterId" type="long">
			<generator class="assigned" />
		</id>
		<property name="attributeName" type="com.liferay.portal.dao.orm.hibernate.StringType" />
		<property name="planUserSettingsId" type="com.liferay.portal.dao.orm.hibernate.LongType" />
		<property name="max" type="com.liferay.portal.dao.orm.hibernate.DoubleType" />
		<property name="min" type="com.liferay.portal.dao.orm.hibernate.DoubleType" />
		<property name="stringVal" type="com.liferay.portal.dao.orm.hibernate.StringType" />
	</class>
	<class name="com.ext.portlet.model.impl.PlanColumnSettingsImpl" table="xcolab_PlanColumnSettings">
		<cache usage="read-write" />
		<id name="planColumnSettingsId" type="long">
			<generator class="assigned" />
		</id>
		<property name="columnName" type="com.liferay.portal.dao.orm.hibernate.StringType" />
		<property name="planUserSettingsId" type="com.liferay.portal.dao.orm.hibernate.LongType" />
		<property name="visible" type="com.liferay.portal.dao.orm.hibernate.BooleanType" />
	</class>
	<class name="com.ext.portlet.model.impl.PlanDescriptionImpl" table="xcolab_PlanDescription">
		<cache usage="read-write" />
		<id name="id" column="id_" type="long">
			<generator class="assigned" />
		</id>
		<property name="planId" type="com.liferay.portal.dao.orm.hibernate.LongType" />
		<property name="name" type="com.liferay.portal.dao.orm.hibernate.StringType" />
		<property name="description" type="com.liferay.portal.dao.orm.hibernate.StringType" />
		<property name="version" type="com.liferay.portal.dao.orm.hibernate.LongType" />
		<property name="planVersion" type="com.liferay.portal.dao.orm.hibernate.LongType" />
		<property name="created" type="org.hibernate.type.TimestampType" />
		<property name="updateAuthorId" type="com.liferay.portal.dao.orm.hibernate.LongType" />
		<property name="image" type="com.liferay.portal.dao.orm.hibernate.LongType" />
		<property name="pitch" type="com.liferay.portal.dao.orm.hibernate.StringType" />
	</class>
	<class name="com.ext.portlet.model.impl.PlanFanImpl" table="xcolab_PlanFan">
		<cache usage="read-write" />
		<id name="id" column="id_" type="long">
			<generator class="assigned" />
		</id>
		<property name="userId" type="com.liferay.portal.dao.orm.hibernate.LongType" />
		<property name="planId" type="com.liferay.portal.dao.orm.hibernate.LongType" />
		<property name="created" type="org.hibernate.type.TimestampType" />
		<property name="deleted" type="org.hibernate.type.TimestampType" />
	</class>
	<class name="com.ext.portlet.model.impl.PlanItemImpl" table="xcolab_PlanItem">
		<cache usage="read-write" />
		<id name="id" column="id_" type="long">
			<generator class="assigned" />
		</id>
		<property name="planId" type="com.liferay.portal.dao.orm.hibernate.LongType" />
		<property name="state" type="com.liferay.portal.dao.orm.hibernate.StringType" column="state_" />
		<property name="updated" type="org.hibernate.type.TimestampType" />
		<property name="updateAuthorId" type="com.liferay.portal.dao.orm.hibernate.LongType" />
		<property name="updateType" type="com.liferay.portal.dao.orm.hibernate.StringType" />
		<property name="version" type="com.liferay.portal.dao.orm.hibernate.LongType" />
	</class>
	<class name="com.ext.portlet.model.impl.PlanItemGroupImpl" table="xcolab_PlanItemGroup">
		<cache usage="read-write" />
		<id name="planId" type="long">
			<generator class="assigned" />
		</id>
		<property name="groupId" type="com.liferay.portal.dao.orm.hibernate.LongType" />
	</class>
	<class name="com.ext.portlet.model.impl.PlanMetaImpl" table="xcolab_PlanMeta">
		<cache usage="read-write" />
		<id name="id" column="id_" type="long">
			<generator class="assigned" />
		</id>
		<property name="planId" type="com.liferay.portal.dao.orm.hibernate.LongType" />
		<property name="planTypeId" type="com.liferay.portal.dao.orm.hibernate.LongType" />
		<property name="planCreated" type="com.liferay.portal.dao.orm.hibernate.LongType" />
		<property name="authorId" type="com.liferay.portal.dao.orm.hibernate.LongType" />
		<property name="votes" type="com.liferay.portal.dao.orm.hibernate.IntegerType" />
		<property name="planGroupId" type="com.liferay.portal.dao.orm.hibernate.LongType" />
		<property name="open" type="com.liferay.portal.dao.orm.hibernate.BooleanType" />
		<property name="status" type="com.liferay.portal.dao.orm.hibernate.StringType" />
		<property name="mbCategoryId" type="com.liferay.portal.dao.orm.hibernate.LongType" />
		<property name="categoryGroupId" type="com.liferay.portal.dao.orm.hibernate.LongType" />
		<property name="version" type="com.liferay.portal.dao.orm.hibernate.LongType" />
		<property name="planVersion" type="com.liferay.portal.dao.orm.hibernate.LongType" />
		<property name="created" type="org.hibernate.type.TimestampType" />
		<property name="updateAuthorId" type="com.liferay.portal.dao.orm.hibernate.LongType" />
		<property name="modelId" type="com.liferay.portal.dao.orm.hibernate.LongType" />
		<property name="promoted" type="com.liferay.portal.dao.orm.hibernate.BooleanType" />
		<property name="previousContestPhase" type="com.liferay.portal.dao.orm.hibernate.LongType" />
		<property name="contestPhase" type="com.liferay.portal.dao.orm.hibernate.LongType" />
	</class>
	<class name="com.ext.portlet.model.impl.PlanModelRunImpl" table="xcolab_PlanModelRun">
		<cache usage="read-write" />
		<id name="id" column="id_" type="long">
			<generator class="assigned" />
		</id>
		<property name="planId" type="com.liferay.portal.dao.orm.hibernate.LongType" />
		<property name="scenarioId" type="com.liferay.portal.dao.orm.hibernate.LongType" />
		<property name="planVersion" type="com.liferay.portal.dao.orm.hibernate.LongType" />
		<property name="version" type="com.liferay.portal.dao.orm.hibernate.LongType" />
		<property name="created" type="org.hibernate.type.TimestampType" />
		<property name="updateAuthorId" type="com.liferay.portal.dao.orm.hibernate.LongType" />
	</class>
	<class name="com.ext.portlet.model.impl.PlanPositionImpl" table="xcolab_PlanPosition">
		<cache usage="read-write" />
		<composite-id name="primaryKey" class="com.ext.portlet.service.persistence.PlanPositionPK">
			<key-property name="planId" type="com.liferay.portal.dao.orm.hibernate.LongType" />
			<key-property name="positionId" type="com.liferay.portal.dao.orm.hibernate.LongType" />
		</composite-id>
		<property name="userId" type="com.liferay.portal.dao.orm.hibernate.LongType" />
		<property name="userName" type="com.liferay.portal.dao.orm.hibernate.StringType" />
		<property name="createDate" type="org.hibernate.type.TimestampType" />
		<property name="modifiedDate" type="org.hibernate.type.TimestampType" />
	</class>
	<class name="com.ext.portlet.model.impl.PlanPositionItemImpl" table="xcolab_PlanPositionItem">
		<cache usage="read-write" />
		<composite-id name="primaryKey" class="com.ext.portlet.service.persistence.PlanPositionItemPK">
			<key-property name="planPositionsId" type="com.liferay.portal.dao.orm.hibernate.LongType" />
			<key-property name="positionId" type="com.liferay.portal.dao.orm.hibernate.LongType" />
		</composite-id>
	</class>
	<class name="com.ext.portlet.model.impl.PlanPositionsImpl" table="xcolab_PlanPositions">
		<cache usage="read-write" />
		<id name="id" column="id_" type="long">
			<generator class="assigned" />
		</id>
		<property name="planId" type="com.liferay.portal.dao.orm.hibernate.LongType" />
		<property name="planVersion" type="com.liferay.portal.dao.orm.hibernate.LongType" />
		<property name="version" type="com.liferay.portal.dao.orm.hibernate.LongType" />
		<property name="created" type="org.hibernate.type.TimestampType" />
		<property name="updateAuthorId" type="com.liferay.portal.dao.orm.hibernate.LongType" />
	</class>
	<class name="com.ext.portlet.model.impl.PlanPropertyFilterImpl" table="xcolab_PlanPropertyFilter">
		<cache usage="read-write" />
		<id name="planPropertyFilterId" type="long">
			<generator class="assigned" />
		</id>
		<property name="propertyName" type="com.liferay.portal.dao.orm.hibernate.StringType" />
		<property name="planUserSettingsId" type="com.liferay.portal.dao.orm.hibernate.LongType" />
		<property name="value" type="com.liferay.portal.dao.orm.hibernate.StringType" />
	</class>
	<class name="com.ext.portlet.model.impl.PlanRelatedImpl" table="xcolab_PlanRelated">
		<cache usage="read-write" />
		<composite-id name="primaryKey" class="com.ext.portlet.service.persistence.PlanRelatedPK">
			<key-property name="sectionId" type="com.liferay.portal.dao.orm.hibernate.LongType" />
			<key-property name="relatedPlanId" type="com.liferay.portal.dao.orm.hibernate.LongType" />
		</composite-id>
	</class>
	<class name="com.ext.portlet.model.impl.PlanSectionImpl" table="xcolab_PlanSection">
		<cache usage="read-write" />
		<id name="id" column="id_" type="long">
			<generator class="assigned" />
		</id>
		<property name="planSectionDefinitionId" type="com.liferay.portal.dao.orm.hibernate.LongType" />
		<property name="planId" type="com.liferay.portal.dao.orm.hibernate.LongType" />
		<property name="content" type="com.liferay.portal.dao.orm.hibernate.StringType" />
		<property name="numericValue" type="com.liferay.portal.dao.orm.hibernate.LongType" />
		<property name="created" type="org.hibernate.type.TimestampType" />
		<property name="version" type="com.liferay.portal.dao.orm.hibernate.LongType" />
		<property name="planVersion" type="com.liferay.portal.dao.orm.hibernate.LongType" />
		<property name="updateAuthorId" type="com.liferay.portal.dao.orm.hibernate.LongType" />
	</class>
	<class name="com.ext.portlet.model.impl.PlanSectionDefinitionImpl" table="xcolab_PlanSectionDefinition">
		<cache usage="read-write" />
		<id name="id" column="id_" type="long">
			<generator class="assigned" />
		</id>
		<property name="type" type="com.liferay.portal.dao.orm.hibernate.StringType" column="type_" />
		<property name="adminTitle" type="com.liferay.portal.dao.orm.hibernate.StringType" />
		<property name="title" type="com.liferay.portal.dao.orm.hibernate.StringType" />
		<property name="defaultText" type="com.liferay.portal.dao.orm.hibernate.StringType" />
		<property name="helpText" type="com.liferay.portal.dao.orm.hibernate.StringType" />
		<property name="characterLimit" type="com.liferay.portal.dao.orm.hibernate.IntegerType" />
		<property name="focusAreaId" type="com.liferay.portal.dao.orm.hibernate.LongType" />
		<property name="tier" type="com.liferay.portal.dao.orm.hibernate.LongType" />
		<property name="locked" type="com.liferay.portal.dao.orm.hibernate.BooleanType" />
	</class>
	<class name="com.ext.portlet.model.impl.PlanSectionPlanMapImpl" table="xcolab_PlanSectionPlanMap">
		<cache usage="read-write" />
		<composite-id name="primaryKey" class="com.ext.portlet.service.persistence.PlanSectionPlanMapPK">
			<key-property name="sectionId" type="com.liferay.portal.dao.orm.hibernate.LongType" />
			<key-property name="relatedPlanId" type="com.liferay.portal.dao.orm.hibernate.LongType" />
		</composite-id>
	</class>
	<class name="com.ext.portlet.model.impl.PlansFilterImpl" table="xcolab_PlansFilter">
		<cache usage="read-write" />
		<composite-id name="primaryKey" class="com.ext.portlet.service.persistence.PlansFilterPK">
			<key-property name="userId" type="com.liferay.portal.dao.orm.hibernate.LongType" />
			<key-property name="planTypeId" type="com.liferay.portal.dao.orm.hibernate.LongType" />
		</composite-id>
		<property name="name" type="com.liferay.portal.dao.orm.hibernate.StringType" />
		<property name="creator" type="com.liferay.portal.dao.orm.hibernate.StringType" />
		<property name="description" type="com.liferay.portal.dao.orm.hibernate.StringType" />
		<property name="CO2From" type="com.liferay.portal.dao.orm.hibernate.DoubleType" />
		<property name="CO2To" type="com.liferay.portal.dao.orm.hibernate.DoubleType" />
		<property name="votesFrom" type="com.liferay.portal.dao.orm.hibernate.DoubleType" />
		<property name="votesTo" type="com.liferay.portal.dao.orm.hibernate.DoubleType" />
		<property name="damageFrom" type="com.liferay.portal.dao.orm.hibernate.DoubleType" />
		<property name="damageTo" type="com.liferay.portal.dao.orm.hibernate.DoubleType" />
		<property name="mitigationFrom" type="com.liferay.portal.dao.orm.hibernate.DoubleType" />
		<property name="mitigationTo" type="com.liferay.portal.dao.orm.hibernate.DoubleType" />
		<property name="dateFrom" type="org.hibernate.type.TimestampType" />
		<property name="dateTo" type="org.hibernate.type.TimestampType" />
		<property name="filterPositionsAll" type="com.liferay.portal.dao.orm.hibernate.BooleanType" />
		<property name="enabled" type="com.liferay.portal.dao.orm.hibernate.BooleanType" />
	</class>
	<class name="com.ext.portlet.model.impl.PlansFilterPositionImpl" table="xcolab_PlansFilterPosition">
		<cache usage="read-write" />
		<composite-id name="primaryKey" class="com.ext.portlet.service.persistence.PlansFilterPositionPK">
			<key-property name="userId" type="com.liferay.portal.dao.orm.hibernate.LongType" />
			<key-property name="planTypeId" type="com.liferay.portal.dao.orm.hibernate.LongType" />
			<key-property name="positionId" type="com.liferay.portal.dao.orm.hibernate.LongType" />
		</composite-id>
	</class>
	<class name="com.ext.portlet.model.impl.PlansUserSettingsImpl" table="xcolab_PlansUserSettings">
		<cache usage="read-write" />
		<id name="planUserSettingsId" type="long">
			<generator class="assigned" />
		</id>
		<property name="userId" type="com.liferay.portal.dao.orm.hibernate.LongType" />
		<property name="planTypeId" type="com.liferay.portal.dao.orm.hibernate.LongType" />
		<property name="sortColumn" type="com.liferay.portal.dao.orm.hibernate.StringType" />
		<property name="sortDirection" type="com.liferay.portal.dao.orm.hibernate.StringType" />
		<property name="filterEnabled" type="com.liferay.portal.dao.orm.hibernate.BooleanType" />
		<property name="filterPositionsAll" type="com.liferay.portal.dao.orm.hibernate.BooleanType" />
	</class>
	<class name="com.ext.portlet.model.impl.PlanTeamHistoryImpl" table="xcolab_PlanTeamHistory">
		<cache usage="read-write" />
		<id name="id" column="id_" type="long">
			<generator class="assigned" />
		</id>
		<property name="planId" type="com.liferay.portal.dao.orm.hibernate.LongType" />
		<property name="userId" type="com.liferay.portal.dao.orm.hibernate.LongType" />
		<property name="action" type="com.liferay.portal.dao.orm.hibernate.StringType" />
		<property name="payload" type="com.liferay.portal.dao.orm.hibernate.StringType" />
		<property name="created" type="org.hibernate.type.TimestampType" />
		<property name="updateAuthorId" type="com.liferay.portal.dao.orm.hibernate.LongType" />
	</class>
	<class name="com.ext.portlet.model.impl.PlanTemplateImpl" table="xcolab_PlanTemplate">
		<cache usage="read-write" />
		<id name="id" column="id_" type="long">
			<generator class="assigned" />
		</id>
		<property name="name" type="com.liferay.portal.dao.orm.hibernate.StringType" />
		<property name="baseTemplateId" type="com.liferay.portal.dao.orm.hibernate.LongType" />
		<property name="impactSeriesTemplateId" type="com.liferay.portal.dao.orm.hibernate.LongType" />
		<property name="focusAreaListTemplateId" type="com.liferay.portal.dao.orm.hibernate.LongType" />
	</class>
	<class name="com.ext.portlet.model.impl.PlanTemplateSectionImpl" table="xcolab_PlanTemplateSection">
		<cache usage="read-write" />
		<composite-id name="primaryKey" class="com.ext.portlet.service.persistence.PlanTemplateSectionPK">
			<key-property name="planTemplateId" type="com.liferay.portal.dao.orm.hibernate.LongType" />
			<key-property name="planSectionId" type="com.liferay.portal.dao.orm.hibernate.LongType" />
		</composite-id>
		<property name="weight" type="com.liferay.portal.dao.orm.hibernate.IntegerType" />
	</class>
	<class name="com.ext.portlet.model.impl.PlanTypeImpl" table="xcolab_PlanType">
		<cache usage="read-write" />
		<id name="planTypeId" type="long">
			<generator class="assigned" />
		</id>
		<property name="name" type="com.liferay.portal.dao.orm.hibernate.StringType" />
		<property name="description" type="com.liferay.portal.dao.orm.hibernate.StringType" />
		<property name="modelId" type="com.liferay.portal.dao.orm.hibernate.LongType" />
		<property name="modelTypeName" type="com.liferay.portal.dao.orm.hibernate.StringType" />
		<property name="published" type="com.liferay.portal.dao.orm.hibernate.BooleanType" />
		<property name="publishedCounterpartId" type="com.liferay.portal.dao.orm.hibernate.LongType" />
		<property name="isDefault" type="com.liferay.portal.dao.orm.hibernate.BooleanType" />
		<property name="defaultModelId" type="com.liferay.portal.dao.orm.hibernate.LongType" />
		<property name="defaultScenarioId" type="com.liferay.portal.dao.orm.hibernate.LongType" />
	</class>
	<class name="com.ext.portlet.model.impl.PlanTypeAttributeImpl" table="xcolab_PlanTypeAttribute">
		<cache usage="read-write" />
		<id name="planTypeAttributeId" type="long">
			<generator class="assigned" />
		</id>
		<property name="planTypeId" type="com.liferay.portal.dao.orm.hibernate.LongType" />
		<property name="attributeName" type="com.liferay.portal.dao.orm.hibernate.StringType" />
	</class>
	<class name="com.ext.portlet.model.impl.PlanTypeColumnImpl" table="xcolab_PlanTypeColumn">
		<cache usage="read-write" />
		<id name="planTypeColumnId" type="long">
			<generator class="assigned" />
		</id>
		<property name="planTypeId" type="com.liferay.portal.dao.orm.hibernate.LongType" />
		<property name="weight" type="com.liferay.portal.dao.orm.hibernate.IntegerType" />
		<property name="columnName" type="com.liferay.portal.dao.orm.hibernate.StringType" />
		<property name="visibleByDefault" type="com.liferay.portal.dao.orm.hibernate.BooleanType" />
	</class>
	<class name="com.ext.portlet.model.impl.PlanVoteImpl" table="xcolab_PlanVote">
		<cache usage="read-write" />
		<composite-id name="primaryKey" class="com.ext.portlet.service.persistence.PlanVotePK">
			<key-property name="userId" type="com.liferay.portal.dao.orm.hibernate.LongType" />
			<key-property name="contestId" type="com.liferay.portal.dao.orm.hibernate.LongType" />
		</composite-id>
		<property name="planId" type="com.liferay.portal.dao.orm.hibernate.LongType" />
		<property name="createDate" type="org.hibernate.type.TimestampType" />
	</class>
	<class name="com.ext.portlet.model.impl.PointDistributionTargetImpl" table="xcolab_PointDistributionTarget">
		<cache usage="read-write" />
		<id name="id" column="id_" type="long">
			<generator class="assigned" />
		</id>
		<property name="contestId" type="com.liferay.portal.dao.orm.hibernate.LongType" />
		<property name="proposalId" type="com.liferay.portal.dao.orm.hibernate.LongType" />
		<property name="numberOfPoints" type="com.liferay.portal.dao.orm.hibernate.DoubleType" />
		<property name="pointTypeOverride" type="com.liferay.portal.dao.orm.hibernate.LongType" />
	</class>
	<class name="com.ext.portlet.model.impl.PointsImpl" table="xcolab_Points">
		<cache usage="read-write" />
		<id name="id" column="id_" type="long">
			<generator class="assigned" />
		</id>
		<property name="proposalId" type="com.liferay.portal.dao.orm.hibernate.LongType" />
		<property name="userId" type="com.liferay.portal.dao.orm.hibernate.LongType" />
		<property name="materializedPoints" type="com.liferay.portal.dao.orm.hibernate.DoubleType" />
		<property name="hypotheticalPoints" type="com.liferay.portal.dao.orm.hibernate.DoubleType" />
		<property name="pointsSourceId" type="com.liferay.portal.dao.orm.hibernate.LongType" />
		<property name="originatingContestPK" type="com.liferay.portal.dao.orm.hibernate.LongType" />
		<property name="originatingProposalId" type="com.liferay.portal.dao.orm.hibernate.LongType" />
	</class>
	<class name="com.ext.portlet.model.impl.PointsDistributionConfigurationImpl" table="xcolab_PointsDistributionConfiguration">
		<cache usage="read-write" />
		<id name="id" column="id_" type="long">
			<generator class="assigned" />
		</id>
		<property name="proposalId" type="com.liferay.portal.dao.orm.hibernate.LongType" />
		<property name="pointTypeId" type="com.liferay.portal.dao.orm.hibernate.LongType" />
		<property name="targetUserId" type="com.liferay.portal.dao.orm.hibernate.LongType" />
		<property name="targetSubProposalId" type="com.liferay.portal.dao.orm.hibernate.LongType" />
		<property name="percentage" type="com.liferay.portal.dao.orm.hibernate.DoubleType" />
		<property name="creator" type="com.liferay.portal.dao.orm.hibernate.LongType" />
		<property name="createDate" type="org.hibernate.type.TimestampType" />
	</class>
	<class name="com.ext.portlet.model.impl.PointTypeImpl" table="xcolab_PointType">
		<cache usage="read-write" />
		<id name="id" column="id_" type="long">
			<generator class="assigned" />
		</id>
		<property name="parentPointTypeId" type="com.liferay.portal.dao.orm.hibernate.LongType" />
		<property name="percentageOfParent" type="com.liferay.portal.dao.orm.hibernate.DoubleType" />
		<property name="distributionStrategy" type="com.liferay.portal.dao.orm.hibernate.StringType" />
		<property name="receiverLimitationStrategy" type="com.liferay.portal.dao.orm.hibernate.StringType" />
		<property name="name" type="com.liferay.portal.dao.orm.hibernate.StringType" />
		<property name="sort" type="com.liferay.portal.dao.orm.hibernate.LongType" />
	</class>
	<class name="com.ext.portlet.model.impl.ProposalImpl" table="xcolab_Proposal">
		<cache usage="read-write" />
		<id name="proposalId" type="long">
			<generator class="assigned" />
		</id>
		<property name="createDate" type="org.hibernate.type.TimestampType" />
		<property name="updatedDate" type="org.hibernate.type.TimestampType" />
		<property name="currentVersion" type="com.liferay.portal.dao.orm.hibernate.IntegerType" />
		<property name="authorId" type="com.liferay.portal.dao.orm.hibernate.LongType" />
		<property name="visible" type="com.liferay.portal.dao.orm.hibernate.BooleanType" />
		<property name="discussionId" type="com.liferay.portal.dao.orm.hibernate.LongType" />
		<property name="resultsDiscussionId" type="com.liferay.portal.dao.orm.hibernate.LongType" />
		<property name="judgeDiscussionId" type="com.liferay.portal.dao.orm.hibernate.LongType" />
		<property name="fellowDiscussionId" type="com.liferay.portal.dao.orm.hibernate.LongType" />
		<property name="advisorDiscussionId" type="com.liferay.portal.dao.orm.hibernate.LongType" />
		<property name="groupId" type="com.liferay.portal.dao.orm.hibernate.LongType" />
	</class>
	<class name="com.ext.portlet.model.impl.Proposal2PhaseImpl" table="xcolab_Proposal2Phase">
		<cache usage="read-write" />
		<composite-id name="primaryKey" class="com.ext.portlet.service.persistence.Proposal2PhasePK">
			<key-property name="proposalId" type="com.liferay.portal.dao.orm.hibernate.LongType" />
			<key-property name="contestPhaseId" type="com.liferay.portal.dao.orm.hibernate.LongType" />
		</composite-id>
		<property name="versionFrom" type="com.liferay.portal.dao.orm.hibernate.IntegerType" />
		<property name="versionTo" type="com.liferay.portal.dao.orm.hibernate.IntegerType" />
		<property name="sortWeight" type="com.liferay.portal.dao.orm.hibernate.IntegerType" />
		<property name="autopromoteCandidate" type="com.liferay.portal.dao.orm.hibernate.BooleanType" />
	</class>
	<class name="com.ext.portlet.model.impl.ProposalAttributeImpl" table="xcolab_ProposalAttribute">
		<cache usage="read-write" />
		<id name="id" column="id_" type="long">
			<generator class="assigned" />
		</id>
		<property name="proposalId" type="com.liferay.portal.dao.orm.hibernate.LongType" />
		<property name="version" type="com.liferay.portal.dao.orm.hibernate.IntegerType" />
		<property name="versionWhenCreated" type="com.liferay.portal.dao.orm.hibernate.IntegerType" />
		<property name="name" type="com.liferay.portal.dao.orm.hibernate.StringType" />
		<property name="additionalId" type="com.liferay.portal.dao.orm.hibernate.LongType" />
		<property name="numericValue" type="com.liferay.portal.dao.orm.hibernate.LongType" />
		<property name="stringValue" type="com.liferay.portal.dao.orm.hibernate.StringType" />
		<property name="realValue" type="com.liferay.portal.dao.orm.hibernate.DoubleType" />
	</class>
	<class name="com.ext.portlet.model.impl.ProposalAttributeTypeImpl" table="xcolab_ProposalAttributeType">
		<cache usage="read-write" />
		<id name="name" type="java.lang.String">
			<generator class="assigned" />
		</id>
		<property name="visibleInVersionHistory" type="com.liferay.portal.dao.orm.hibernate.BooleanType" />
		<property name="copyOnPromote" type="com.liferay.portal.dao.orm.hibernate.BooleanType" />
	</class>
	<class name="com.ext.portlet.model.impl.ProposalContestPhaseAttributeImpl" table="xcolab_ProposalContestPhaseAttribute">
		<cache usage="read-write" />
		<id name="id" column="id_" type="long">
			<generator class="assigned" />
		</id>
		<property name="proposalId" type="com.liferay.portal.dao.orm.hibernate.LongType" />
		<property name="contestPhaseId" type="com.liferay.portal.dao.orm.hibernate.LongType" />
		<property name="name" type="com.liferay.portal.dao.orm.hibernate.StringType" />
		<property name="additionalId" type="com.liferay.portal.dao.orm.hibernate.LongType" />
		<property name="numericValue" type="com.liferay.portal.dao.orm.hibernate.LongType" />
		<property name="stringValue" type="com.liferay.portal.dao.orm.hibernate.StringType" />
		<property name="realValue" type="com.liferay.portal.dao.orm.hibernate.DoubleType" />
	</class>
	<class name="com.ext.portlet.model.impl.ProposalContestPhaseAttributeTypeImpl" table="xcolab_ProposalContestPhaseAttributeType">
		<cache usage="read-write" />
		<id name="name" type="java.lang.String">
			<generator class="assigned" />
		</id>
		<property name="copyOnPromote" type="com.liferay.portal.dao.orm.hibernate.BooleanType" />
	</class>
	<class name="com.ext.portlet.model.impl.ProposalRatingImpl" table="xcolab_ProposalRating">
		<cache usage="read-write" />
		<id name="id" column="id_" type="long">
			<generator class="assigned" />
		</id>
		<property name="proposalId" type="com.liferay.portal.dao.orm.hibernate.LongType" />
		<property name="contestPhaseId" type="com.liferay.portal.dao.orm.hibernate.LongType" />
		<property name="userId" type="com.liferay.portal.dao.orm.hibernate.LongType" />
		<property name="ratingValueId" type="com.liferay.portal.dao.orm.hibernate.LongType" />
		<property name="comment" type="com.liferay.portal.dao.orm.hibernate.StringType" column="comment_" />
		<property name="commentEnabled" type="com.liferay.portal.dao.orm.hibernate.BooleanType" />
		<property name="otherDataString" type="com.liferay.portal.dao.orm.hibernate.StringType" />
	</class>
	<class name="com.ext.portlet.model.impl.ProposalRatingTypeImpl" table="xcolab_ProposalRatingType">
		<cache usage="read-write" />
		<id name="id" column="id_" type="long">
			<generator class="assigned" />
		</id>
		<property name="label" type="com.liferay.portal.dao.orm.hibernate.StringType" />
		<property name="description" type="com.liferay.portal.dao.orm.hibernate.StringType" />
		<property name="judgeType" type="com.liferay.portal.dao.orm.hibernate.IntegerType" />
		<property name="isActive" type="com.liferay.portal.dao.orm.hibernate.BooleanType" />
	</class>
	<class name="com.ext.portlet.model.impl.ProposalRatingValueImpl" table="xcolab_ProposalRatingValue">
		<cache usage="read-write" />
		<id name="id" column="id_" type="long">
			<generator class="assigned" />
		</id>
		<property name="ratingTypeId" type="com.liferay.portal.dao.orm.hibernate.LongType" />
		<property name="value" type="com.liferay.portal.dao.orm.hibernate.LongType" />
		<property name="name" type="com.liferay.portal.dao.orm.hibernate.StringType" />
		<property name="description" type="com.liferay.portal.dao.orm.hibernate.StringType" />
	</class>
	<class name="com.ext.portlet.model.impl.ProposalSupporterImpl" table="xcolab_ProposalSupporter">
		<cache usage="read-write" />
		<composite-id name="primaryKey" class="com.ext.portlet.service.persistence.ProposalSupporterPK">
			<key-property name="proposalId" type="com.liferay.portal.dao.orm.hibernate.LongType" />
			<key-property name="userId" type="com.liferay.portal.dao.orm.hibernate.LongType" />
		</composite-id>
		<property name="createDate" type="org.hibernate.type.TimestampType" />
	</class>
	<class name="com.ext.portlet.model.impl.ProposalVersionImpl" table="xcolab_ProposalVersion">
		<cache usage="read-write" />
		<composite-id name="primaryKey" class="com.ext.portlet.service.persistence.ProposalVersionPK">
			<key-property name="proposalId" type="com.liferay.portal.dao.orm.hibernate.LongType" />
			<key-property name="version" type="com.liferay.portal.dao.orm.hibernate.IntegerType" />
		</composite-id>
		<property name="authorId" type="com.liferay.portal.dao.orm.hibernate.LongType" />
		<property name="createDate" type="org.hibernate.type.TimestampType" />
		<property name="updateType" type="com.liferay.portal.dao.orm.hibernate.StringType" />
		<property name="updateAdditionalId" type="com.liferay.portal.dao.orm.hibernate.LongType" />
	</class>
	<class name="com.ext.portlet.model.impl.ProposalVoteImpl" table="xcolab_ProposalVote">
		<cache usage="read-write" />
		<composite-id name="primaryKey" class="com.ext.portlet.service.persistence.ProposalVotePK">
			<key-property name="contestPhaseId" type="com.liferay.portal.dao.orm.hibernate.LongType" />
			<key-property name="userId" type="com.liferay.portal.dao.orm.hibernate.LongType" />
		</composite-id>
		<property name="proposalId" type="com.liferay.portal.dao.orm.hibernate.LongType" />
		<property name="createDate" type="org.hibernate.type.TimestampType" />
	</class>
	<class name="com.ext.portlet.model.impl.Role_Impl" table="xcolab_Role_">
		<cache usage="read-write" />
		<id name="roleId" type="long">
			<generator class="assigned" />
		</id>
		<property name="name" type="com.liferay.portal.dao.orm.hibernate.StringType" />
	</class>
	<class name="com.ext.portlet.model.impl.RolesCategoryImpl" table="xcolab_RolesCategory">
		<cache usage="read-write" />
		<id name="roleId" type="long">
			<generator class="assigned" />
		</id>
		<property name="categoryName" type="com.liferay.portal.dao.orm.hibernate.StringType" />
		<property name="roleOrdinal" type="com.liferay.portal.dao.orm.hibernate.IntegerType" />
	</class>
	<class name="com.ext.portlet.model.impl.SocialActivityImpl" table="xcolab_SocialActivity">
		<cache usage="read-write" />
		<id name="activityId" type="long">
			<generator class="assigned" />
		</id>
		<property name="userId" type="com.liferay.portal.dao.orm.hibernate.LongType" />
	</class>
	<class name="com.ext.portlet.model.impl.StaffMemberImpl" table="xcolab_StaffMember">
		<cache usage="read-write" />
		<id name="id" column="id_" type="long">
			<generator class="assigned" />
		</id>
		<property name="userId" type="com.liferay.portal.dao.orm.hibernate.LongType" />
		<property name="categoryId" type="com.liferay.portal.dao.orm.hibernate.LongType" />
		<property name="firstNames" type="com.liferay.portal.dao.orm.hibernate.StringType" />
		<property name="lastName" type="com.liferay.portal.dao.orm.hibernate.StringType" />
		<property name="url" type="com.liferay.portal.dao.orm.hibernate.StringType" />
		<property name="photoUrl" type="com.liferay.portal.dao.orm.hibernate.StringType" />
		<property name="role" type="com.liferay.portal.dao.orm.hibernate.StringType" />
		<property name="organization" type="com.liferay.portal.dao.orm.hibernate.StringType" />
		<property name="sort" type="com.liferay.portal.dao.orm.hibernate.IntegerType" />
	</class>
	<class name="com.ext.portlet.model.impl.TrackedVisitImpl" table="xcolab_TrackedVisit">
		<cache usage="read-write" />
		<id name="id" column="id_" type="long">
			<generator class="assigned" />
		</id>
		<property name="uuid" type="com.liferay.portal.dao.orm.hibernate.StringType" column="uuid_" />
		<property name="ip" type="com.liferay.portal.dao.orm.hibernate.StringType" />
		<property name="city" type="com.liferay.portal.dao.orm.hibernate.StringType" />
		<property name="country" type="com.liferay.portal.dao.orm.hibernate.StringType" />
		<property name="url" type="com.liferay.portal.dao.orm.hibernate.StringType" />
		<property name="browser" type="com.liferay.portal.dao.orm.hibernate.StringType" />
		<property name="headers" type="com.liferay.portal.dao.orm.hibernate.StringType" />
		<property name="referer" type="com.liferay.portal.dao.orm.hibernate.StringType" />
		<property name="createDate" type="org.hibernate.type.TimestampType" />
	</class>
	<class name="com.ext.portlet.model.impl.TrackedVisitor2UserImpl" table="xcolab_TrackedVisitor2User">
		<cache usage="read-write" />
		<id name="id" column="id_" type="long">
			<generator class="assigned" />
		</id>
		<property name="uuid" type="com.liferay.portal.dao.orm.hibernate.StringType" column="uuid_" />
		<property name="userId" type="com.liferay.portal.dao.orm.hibernate.LongType" />
		<property name="createDate" type="org.hibernate.type.TimestampType" />
	</class>
	<class name="com.ext.portlet.model.impl.User_Impl" table="xcolab_User_">
		<cache usage="read-write" />
		<id name="userId" type="long">
			<generator class="assigned" />
		</id>
		<property name="createDate" type="org.hibernate.type.TimestampType" />
		<property name="screenName" type="com.liferay.portal.dao.orm.hibernate.StringType" />
	</class>
	<class name="com.ext.portlet.model.impl.Users_RolesImpl" table="xcolab_Users_Roles">
		<cache usage="read-write" />
		<composite-id name="primaryKey" class="com.ext.portlet.service.persistence.Users_RolesPK">
			<key-property name="userId" type="com.liferay.portal.dao.orm.hibernate.LongType" />
			<key-property name="roleId" type="com.liferay.portal.dao.orm.hibernate.LongType" />
		</composite-id>
	</class>
</hibernate-mapping>